torchflow/__init__.py
torchflow/flow.py
torchflow/flow_test.py
torchflow/mnist_flow.py
torchflow-0.0.3.dist-info/METADATA
torchflow-0.0.3.dist-info/WHEEL
torchflow-0.0.3.dist-info/top_level.txt
torchflow-0.0.3.dist-info/RECORD
