Metadata-Version: 2.1
Name: torchflow
Version: 0.0.3
Summary: PyTorch modules for Normalizing Flows.
Home-page: https://github.com/PiotrDabkowski/torchflow
Author: Piotr Dabkowski
Author-email: UNKNOWN
License: MIT
Platform: UNKNOWN
Requires-Dist: torch
Requires-Dist: numpy
